sebs/__init__.py
sebs/apps.py
sebs/backend.py
sebs/tests/__init__.py
sebs/tests/conftest.py
sebs/tests/test_backend.py
django_sebs-0.2.0.dist-info/LICENSE
django_sebs-0.2.0.dist-info/METADATA
django_sebs-0.2.0.dist-info/WHEEL
django_sebs-0.2.0.dist-info/top_level.txt
django_sebs-0.2.0.dist-info/RECORD
